{"_id":"karma-spec-reporter","_rev":"67-4d464b9e27dee09333dc6f96fa3af978","name":"karma-spec-reporter","description":"A Karma plugin. Report all spec-results to console (like mocha's spec reporter).","dist-tags":{"latest":"0.0.26"},"versions":{"0.0.1":{"name":"karma-spec-reporter","version":"0.0.1","description":"A Karma plugin. Report all spec-results to console (like mocha's spec reporter).","main":"index.js","scripts":{"test":"echo \"Error: no test specified\" && exit 1"},"repository":{"type":"git","url":"git://github.com/mlex/karma-spec-reporter.git"},"keywords":["karma-plugin","reporter"],"author":{"name":"Michael Lex","email":"michael.lex@codecentric.de"},"dependencies":{"colors":"~0.6.0"},"peerDependencies":{"karma":"~0.9"},"license":"MIT","_id":"karma-spec-reporter@0.0.1","dist":{"shasum":"3a5fa09076e6f783d73d524e57480b306c2bd41d","tarball":"https://registry.npmjs.org/karma-spec-reporter/-/karma-spec-reporter-0.0.1.tgz"},"_from":".","_npmVersion":"1.2.18","_npmUser":{"name":"mlex","email":"mich.lex@gmail.com"},"maintainers":[{"name":"mlex","email":"mich.lex@gmail.com"}],"directories":{}},"0.0.2":{"name":"karma-spec-reporter","version":"0.0.2","description":"A Karma plugin. Report all spec-results to console (like mocha's spec reporter).","main":"index.js","scripts":{"test":"echo \"Error: no test specified\" && exit 1"},"repository":{"type":"git","url":"git://github.com/mlex/karma-spec-reporter.git"},"keywords":["karma-plugin","reporter"],"author":{"name":"Michael Lex","email":"michael.lex@codecentric.de"},"dependencies":{"colors":"~0.6.0"},"peerDependencies":{"karma":"~0.9"},"license":"MIT","_id":"karma-spec-reporter@0.0.2","dist":{"shasum":"47e9cd7fd88da8b9c45dc3272ce4f9bff8a59bfa","tarball":"https://registry.npmjs.org/karma-spec-reporter/-/karma-spec-reporter-0.0.2.tgz"},"_from":".","_npmVersion":"1.2.18","_npmUser":{"name":"mlex","email":"mich.lex@gmail.com"},"maintainers":[{"name":"mlex","email":"mich.lex@gmail.com"}],"directories":{}},"0.0.3":{"name":"karma-spec-reporter","version":"0.0.3","description":"A Karma plugin. Report all spec-results to console (like mocha's spec reporter).","main":"index.js","scripts":{"test":"echo \"Error: no test specified\" && exit 1"},"repository":{"type":"git","url":"git://github.com/mlex/karma-spec-reporter.git"},"keywords":["karma-plugin","reporter"],"author":{"name":"Michael Lex","email":"michael.lex@codecentric.de"},"dependencies":{"colors":"~0.6.0"},"peerDependencies":{"karma":"~0.9"},"license":"MIT","_id":"karma-spec-reporter@0.0.3","dist":{"shasum":"5e85cc2581d92905347088e3f88d8421d10faf31","tarball":"https://registry.npmjs.org/karma-spec-reporter/-/karma-spec-reporter-0.0.3.tgz"},"_from":".","_npmVersion":"1.2.18","_npmUser":{"name":"mlex","email":"mich.lex@gmail.com"},"maintainers":[{"name":"mlex","email":"mich.lex@gmail.com"}],"directories":{}},"0.0.4":{"name":"karma-spec-reporter","version":"0.0.4","description":"A Karma plugin. Report all spec-results to console (like mocha's spec reporter).","main":"index.js","scripts":{"test":"echo \"Error: no test specified\" && exit 1"},"repository":{"type":"git","url":"git://github.com/mlex/karma-spec-reporter.git"},"keywords":["karma-plugin","reporter"],"author":{"name":"Michael Lex","email":"michael.lex@codecentric.de"},"dependencies":{"colors":"~0.6.0"},"peerDependencies":{"karma":">=0.9"},"license":"MIT","_id":"karma-spec-reporter@0.0.4","dist":{"shasum":"30aac565b9d4a4aa13db0566989bc257731eb751","tarball":"https://registry.npmjs.org/karma-spec-reporter/-/karma-spec-reporter-0.0.4.tgz"},"_from":".","_npmVersion":"1.2.18","_npmUser":{"name":"mlex","email":"mich.lex@gmail.com"},"maintainers":[{"name":"mlex","email":"mich.lex@gmail.com"}],"directories":{}},"0.0.5":{"name":"karma-spec-reporter","version":"0.0.5","description":"A Karma plugin. Report all spec-results to console (like mocha's spec reporter).","main":"index.js","scripts":{"test":"echo \"Error: no test specified\" && exit 1"},"repository":{"type":"git","url":"git://github.com/mlex/karma-spec-reporter.git"},"keywords":["karma-plugin","reporter"],"author":{"name":"Michael Lex","email":"michael.lex@codecentric.de"},"dependencies":{"colors":"~0.6.0"},"peerDependencies":{"karma":">=0.9"},"license":"MIT","_id":"karma-spec-reporter@0.0.5","dist":{"shasum":"6cb1c667467a7e8bee32da503071805642b969ce","tarball":"https://registry.npmjs.org/karma-spec-reporter/-/karma-spec-reporter-0.0.5.tgz"},"_from":".","_npmVersion":"1.2.18","_npmUser":{"name":"mlex","email":"mich.lex@gmail.com"},"maintainers":[{"name":"mlex","email":"mich.lex@gmail.com"}],"directories":{}},"0.0.6":{"name":"karma-spec-reporter","version":"0.0.6","description":"A Karma plugin. Report all spec-results to console (like mocha's spec reporter).","main":"index.js","scripts":{"test":"echo \"Error: no test specified\" && exit 1"},"repository":{"type":"git","url":"git://github.com/mlex/karma-spec-reporter.git"},"keywords":["karma-plugin","reporter"],"author":{"name":"Michael Lex","email":"michael.lex@codecentric.de"},"dependencies":{"colors":"~0.6.0"},"peerDependencies":{"karma":">=0.9"},"license":"MIT","_id":"karma-spec-reporter@0.0.6","dist":{"shasum":"e774af5e7ecb7ed868af93785a726dd33152149d","tarball":"https://registry.npmjs.org/karma-spec-reporter/-/karma-spec-reporter-0.0.6.tgz"},"_from":".","_npmVersion":"1.2.18","_npmUser":{"name":"mlex","email":"mich.lex@gmail.com"},"maintainers":[{"name":"mlex","email":"mich.lex@gmail.com"}],"directories":{}},"0.0.7":{"name":"karma-spec-reporter","version":"0.0.7","description":"A Karma plugin. Report all spec-results to console (like mocha's spec reporter).","main":"index.js","scripts":{"test":"echo \"Error: no test specified\" && exit 1"},"repository":{"type":"git","url":"git://github.com/mlex/karma-spec-reporter.git"},"keywords":["karma-plugin","reporter"],"author":{"name":"Michael Lex","email":"michael.lex@codecentric.de"},"dependencies":{"colors":"~0.6.0"},"peerDependencies":{"karma":">=0.9"},"license":"MIT","_id":"karma-spec-reporter@0.0.7","dist":{"shasum":"a98e307006e501e158e4649adfb2b311b9475adf","tarball":"https://registry.npmjs.org/karma-spec-reporter/-/karma-spec-reporter-0.0.7.tgz"},"_from":".","_npmVersion":"1.2.18","_npmUser":{"name":"mlex","email":"mich.lex@gmail.com"},"maintainers":[{"name":"mlex","email":"mich.lex@gmail.com"}],"directories":{}},"0.0.8":{"name":"karma-spec-reporter","version":"0.0.8","description":"A Karma plugin. Report all spec-results to console (like mocha's spec reporter).","main":"index.js","scripts":{"test":"echo \"Error: no test specified\" && exit 1"},"repository":{"type":"git","url":"git://github.com/mlex/karma-spec-reporter.git"},"keywords":["karma-plugin","reporter"],"author":{"name":"Michael Lex","email":"michael.lex@codecentric.de"},"dependencies":{"colors":"~0.6.0"},"peerDependencies":{"karma":">=0.9"},"license":"MIT","_id":"karma-spec-reporter@0.0.8","dist":{"shasum":"f09cbecb1ecb5f087ae1cf21baee3b89eddacc47","tarball":"https://registry.npmjs.org/karma-spec-reporter/-/karma-spec-reporter-0.0.8.tgz"},"_from":".","_npmVersion":"1.2.18","_npmUser":{"name":"mlex","email":"mich.lex@gmail.com"},"maintainers":[{"name":"mlex","email":"mich.lex@gmail.com"}],"directories":{}},"0.0.9":{"name":"karma-spec-reporter","version":"0.0.9","description":"A Karma plugin. Report all spec-results to console (like mocha's spec reporter).","main":"index.js","scripts":{"test":"echo \"Error: no test specified\" && exit 1"},"repository":{"type":"git","url":"git://github.com/mlex/karma-spec-reporter.git"},"keywords":["karma-plugin","reporter"],"author":{"name":"Michael Lex","email":"michael.lex@codecentric.de"},"dependencies":{"colors":"~0.6.0"},"peerDependencies":{"karma":">=0.9"},"license":"MIT","_id":"karma-spec-reporter@0.0.9","dist":{"shasum":"acc786acb4937e9d5bd511738e6910d3a8405f48","tarball":"https://registry.npmjs.org/karma-spec-reporter/-/karma-spec-reporter-0.0.9.tgz"},"_from":".","_npmVersion":"1.2.18","_npmUser":{"name":"mlex","email":"mich.lex@gmail.com"},"maintainers":[{"name":"mlex","email":"mich.lex@gmail.com"}],"directories":{}},"0.0.10":{"name":"karma-spec-reporter","version":"0.0.10","description":"A Karma plugin. Report all spec-results to console (like mocha's spec reporter).","main":"index.js","scripts":{"test":"echo \"Error: no test specified\" && exit 1"},"repository":{"type":"git","url":"git://github.com/mlex/karma-spec-reporter.git"},"keywords":["karma-plugin","reporter"],"author":{"name":"Michael Lex","email":"michael.lex@codecentric.de"},"dependencies":{"colors":"~0.6.0"},"peerDependencies":{"karma":">=0.9"},"license":"MIT","bugs":{"url":"https://github.com/mlex/karma-spec-reporter/issues"},"homepage":"https://github.com/mlex/karma-spec-reporter","_id":"karma-spec-reporter@0.0.10","dist":{"shasum":"094ea3a460716019b60e439197685607610c5ca4","tarball":"https://registry.npmjs.org/karma-spec-reporter/-/karma-spec-reporter-0.0.10.tgz"},"_from":".","_npmVersion":"1.4.4","_npmUser":{"name":"mlex","email":"mich.lex@gmail.com"},"maintainers":[{"name":"mlex","email":"mich.lex@gmail.com"}],"directories":{}},"0.0.11":{"name":"karma-spec-reporter","version":"0.0.11","description":"A Karma plugin. Report all spec-results to console (like mocha's spec reporter).","main":"index.js","scripts":{"test":"echo \"Error: no test specified\" && exit 1"},"repository":{"type":"git","url":"git://github.com/mlex/karma-spec-reporter.git"},"keywords":["karma-plugin","reporter"],"author":{"name":"Michael Lex","email":"michael.lex@codecentric.de"},"dependencies":{"colors":"~0.6.0"},"peerDependencies":{"karma":">=0.9"},"license":"MIT","_id":"karma-spec-reporter@0.0.11","dist":{"shasum":"8aef94362878e096537b1b233347bddf133f43e9","tarball":"https://registry.npmjs.org/karma-spec-reporter/-/karma-spec-reporter-0.0.11.tgz"},"_from":".","_npmVersion":"1.2.18","_npmUser":{"name":"mlex","email":"mich.lex@gmail.com"},"maintainers":[{"name":"mlex","email":"mich.lex@gmail.com"}],"directories":{}},"0.0.12":{"name":"karma-spec-reporter","version":"0.0.12","description":"A Karma plugin. Report all spec-results to console (like mocha's spec reporter).","main":"index.js","scripts":{"test":"echo \"Error: no test specified\" && exit 1"},"repository":{"type":"git","url":"git://github.com/mlex/karma-spec-reporter.git"},"keywords":["karma-plugin","reporter"],"author":{"name":"Michael Lex","email":"michael.lex@codecentric.de"},"dependencies":{"colors":"~0.6.0"},"peerDependencies":{"karma":">=0.9"},"license":"MIT","_id":"karma-spec-reporter@0.0.12","dist":{"shasum":"24b96efded15b80bb6b9f67783efb6e73c2bfb91","tarball":"https://registry.npmjs.org/karma-spec-reporter/-/karma-spec-reporter-0.0.12.tgz"},"_from":".","_npmVersion":"1.2.18","_npmUser":{"name":"mlex","email":"mich.lex@gmail.com"},"maintainers":[{"name":"mlex","email":"mich.lex@gmail.com"}],"directories":{}},"0.0.13":{"name":"karma-spec-reporter","version":"0.0.13","description":"A Karma plugin. Report all spec-results to console (like mocha's spec reporter).","main":"index.js","scripts":{"test":"echo \"Error: no test specified\" && exit 1"},"repository":{"type":"git","url":"git://github.com/mlex/karma-spec-reporter.git"},"keywords":["karma-plugin","reporter"],"author":{"name":"Michael Lex","email":"michael.lex@codecentric.de"},"dependencies":{"colors":"~0.6.0"},"peerDependencies":{"karma":">=0.9"},"license":"MIT","_id":"karma-spec-reporter@0.0.13","dist":{"shasum":"7e6b9546a3c67a9a7d0ec45984398df7fd4aac6a","tarball":"https://registry.npmjs.org/karma-spec-reporter/-/karma-spec-reporter-0.0.13.tgz"},"_from":".","_npmVersion":"1.2.18","_npmUser":{"name":"mlex","email":"mich.lex@gmail.com"},"maintainers":[{"name":"mlex","email":"mich.lex@gmail.com"}],"directories":{}},"0.0.14":{"name":"karma-spec-reporter","version":"0.0.14","description":"A Karma plugin. Report all spec-results to console (like mocha's spec reporter).","main":"index.js","scripts":{"test":"echo \"Error: no test specified\" && exit 1"},"repository":{"type":"git","url":"git://github.com/mlex/karma-spec-reporter.git"},"keywords":["karma-plugin","reporter"],"author":{"name":"Michael Lex","email":"michael.lex@codecentric.de"},"dependencies":{"colors":"~0.6.0"},"peerDependencies":{"karma":">=0.9"},"license":"MIT","_id":"karma-spec-reporter@0.0.14","dist":{"shasum":"92f21e5a72ba6ca352f844628a7f17060794fc67","tarball":"https://registry.npmjs.org/karma-spec-reporter/-/karma-spec-reporter-0.0.14.tgz"},"_from":".","_npmVersion":"1.2.18","_npmUser":{"name":"mlex","email":"mich.lex@gmail.com"},"maintainers":[{"name":"mlex","email":"mich.lex@gmail.com"}],"directories":{}},"0.0.15":{"name":"karma-spec-reporter","version":"0.0.15","description":"A Karma plugin. Report all spec-results to console (like mocha's spec reporter).","main":"index.js","scripts":{"test":"echo \"Error: no test specified\" && exit 1"},"repository":{"type":"git","url":"git://github.com/mlex/karma-spec-reporter.git"},"keywords":["karma-plugin","reporter"],"author":{"name":"Michael Lex","email":"michael.lex@codecentric.de"},"dependencies":{"colors":"~0.6.0"},"peerDependencies":{"karma":">=0.9"},"license":"MIT","_id":"karma-spec-reporter@0.0.15","dist":{"shasum":"86140764e87eb4a78a3f61822181fb885e1e0abd","tarball":"https://registry.npmjs.org/karma-spec-reporter/-/karma-spec-reporter-0.0.15.tgz"},"_from":".","_npmVersion":"1.2.18","_npmUser":{"name":"mlex","email":"mich.lex@gmail.com"},"maintainers":[{"name":"mlex","email":"mich.lex@gmail.com"}],"directories":{}},"0.0.16":{"name":"karma-spec-reporter","version":"0.0.16","description":"A Karma plugin. Report all spec-results to console (like mocha's spec reporter).","main":"index.js","scripts":{"test":"echo \"Error: no test specified\" && exit 1"},"repository":{"type":"git","url":"git://github.com/mlex/karma-spec-reporter.git"},"keywords":["karma-plugin","reporter"],"author":{"name":"Michael Lex","email":"michael.lex@codecentric.de"},"dependencies":{"colors":"~0.6.0"},"peerDependencies":{"karma":">=0.9"},"license":"MIT","_id":"karma-spec-reporter@0.0.16","dist":{"shasum":"331b65c825c301eb0af9e066a464bb9ef4b355b3","tarball":"https://registry.npmjs.org/karma-spec-reporter/-/karma-spec-reporter-0.0.16.tgz"},"_from":".","_npmVersion":"1.2.18","_npmUser":{"name":"mlex","email":"mich.lex@gmail.com"},"maintainers":[{"name":"mlex","email":"mich.lex@gmail.com"}],"directories":{}},"0.0.17":{"name":"karma-spec-reporter","version":"0.0.17","description":"A Karma plugin. Report all spec-results to console (like mocha's spec reporter).","main":"index.js","scripts":{"test":"echo \"Error: no test specified\" && exit 1"},"repository":{"type":"git","url":"git://github.com/mlex/karma-spec-reporter.git"},"keywords":["karma-plugin","reporter"],"author":{"name":"Michael Lex","email":"michael.lex@codecentric.de"},"dependencies":{"colors":"~0.6.0"},"peerDependencies":{"karma":">=0.9"},"license":"MIT","gitHead":"9342dfb5d31cb02afb87510b8cf45785ae57f1c0","bugs":{"url":"https://github.com/mlex/karma-spec-reporter/issues"},"homepage":"https://github.com/mlex/karma-spec-reporter","_id":"karma-spec-reporter@0.0.17","_shasum":"a8da714e45d9b14c1aa2db7be8398f1d2b1fab01","_from":".","_npmVersion":"1.4.28","_npmUser":{"name":"mlex","email":"mich.lex@gmail.com"},"maintainers":[{"name":"mlex","email":"mich.lex@gmail.com"}],"dist":{"shasum":"a8da714e45d9b14c1aa2db7be8398f1d2b1fab01","tarball":"https://registry.npmjs.org/karma-spec-reporter/-/karma-spec-reporter-0.0.17.tgz"},"directories":{}},"0.0.18":{"name":"karma-spec-reporter","version":"0.0.18","description":"A Karma plugin. Report all spec-results to console (like mocha's spec reporter).","main":"index.js","scripts":{"test":"echo \"Error: no test specified\" && exit 1"},"repository":{"type":"git","url":"git://github.com/mlex/karma-spec-reporter.git"},"keywords":["karma-plugin","reporter"],"author":{"name":"Michael Lex","email":"michael.lex@codecentric.de"},"dependencies":{"colors":"~0.6.0"},"peerDependencies":{"karma":">=0.9"},"license":"MIT","gitHead":"481ab126ff120519a1c12bac681957f5e400bd73","bugs":{"url":"https://github.com/mlex/karma-spec-reporter/issues"},"homepage":"https://github.com/mlex/karma-spec-reporter","_id":"karma-spec-reporter@0.0.18","_shasum":"8fc90f01b9c0a76ec841479c24564e1d90ace3a3","_from":".","_npmVersion":"1.4.28","_npmUser":{"name":"mlex","email":"mich.lex@gmail.com"},"maintainers":[{"name":"mlex","email":"mich.lex@gmail.com"}],"dist":{"shasum":"8fc90f01b9c0a76ec841479c24564e1d90ace3a3","tarball":"https://registry.npmjs.org/karma-spec-reporter/-/karma-spec-reporter-0.0.18.tgz"},"directories":{}},"0.0.19":{"name":"karma-spec-reporter","version":"0.0.19","description":"A Karma plugin. Report all spec-results to console (like mocha's spec reporter).","main":"index.js","scripts":{"test":"echo \"Error: no test specified\" && exit 1"},"repository":{"type":"git","url":"git://github.com/mlex/karma-spec-reporter.git"},"keywords":["karma-plugin","reporter"],"author":{"name":"Michael Lex","email":"michael.lex@codecentric.de"},"dependencies":{"colors":"~0.6.0"},"peerDependencies":{"karma":">=0.9"},"license":"MIT","gitHead":"a045ed1b25fba61516ee04ccf9bcf736b02f4caf","bugs":{"url":"https://github.com/mlex/karma-spec-reporter/issues"},"homepage":"https://github.com/mlex/karma-spec-reporter","_id":"karma-spec-reporter@0.0.19","_shasum":"d86b48df5108d615311d4c419ac4db7d68a7b021","_from":".","_npmVersion":"1.4.28","_npmUser":{"name":"mlex","email":"mich.lex@gmail.com"},"maintainers":[{"name":"mlex","email":"mich.lex@gmail.com"}],"dist":{"shasum":"d86b48df5108d615311d4c419ac4db7d68a7b021","tarball":"https://registry.npmjs.org/karma-spec-reporter/-/karma-spec-reporter-0.0.19.tgz"},"directories":{}},"0.0.20":{"name":"karma-spec-reporter","version":"0.0.20","description":"A Karma plugin. Report all spec-results to console (like mocha's spec reporter).","main":"index.js","scripts":{"test":"echo \"Error: no test specified\" && exit 1"},"repository":{"type":"git","url":"git://github.com/mlex/karma-spec-reporter.git"},"keywords":["karma-plugin","reporter"],"author":{"name":"Michael Lex","email":"michael.lex@codecentric.de"},"dependencies":{"colors":"~0.6.0"},"peerDependencies":{"karma":">=0.9"},"license":"MIT","gitHead":"b0abf6b53c6ef7328392362aa9386caae410779f","bugs":{"url":"https://github.com/mlex/karma-spec-reporter/issues"},"homepage":"https://github.com/mlex/karma-spec-reporter","_id":"karma-spec-reporter@0.0.20","_shasum":"7e2692c35c8321ea779136dbb356be3aa6e3240d","_from":".","_npmVersion":"1.4.28","_npmUser":{"name":"mlex","email":"mich.lex@gmail.com"},"maintainers":[{"name":"mlex","email":"mich.lex@gmail.com"}],"dist":{"shasum":"7e2692c35c8321ea779136dbb356be3aa6e3240d","tarball":"https://registry.npmjs.org/karma-spec-reporter/-/karma-spec-reporter-0.0.20.tgz"},"directories":{}},"0.0.21":{"name":"karma-spec-reporter","version":"0.0.21","description":"A Karma plugin. Report all spec-results to console (like mocha's spec reporter).","main":"index.js","scripts":{"test":"echo \"Error: no test specified\" && exit 1"},"repository":{"type":"git","url":"git://github.com/mlex/karma-spec-reporter.git"},"keywords":["karma-plugin","reporter"],"author":{"name":"Michael Lex","email":"michael.lex@codecentric.de"},"dependencies":{"colors":"~0.6.0"},"peerDependencies":{"karma":">=0.9"},"license":"MIT","gitHead":"1cd4535f557127b439c0e53dfd48ff8e353892c6","bugs":{"url":"https://github.com/mlex/karma-spec-reporter/issues"},"homepage":"https://github.com/mlex/karma-spec-reporter","_id":"karma-spec-reporter@0.0.21","_shasum":"b2a8988771afd1e3e56824f042d0fa8e86651942","_from":".","_npmVersion":"1.4.28","_npmUser":{"name":"mlex","email":"mich.lex@gmail.com"},"maintainers":[{"name":"mlex","email":"mich.lex@gmail.com"}],"dist":{"shasum":"b2a8988771afd1e3e56824f042d0fa8e86651942","tarball":"https://registry.npmjs.org/karma-spec-reporter/-/karma-spec-reporter-0.0.21.tgz"},"directories":{}},"0.0.22":{"name":"karma-spec-reporter","version":"0.0.22","description":"A Karma plugin. Report all spec-results to console (like mocha's spec reporter).","main":"index.js","scripts":{"test":"echo \"Error: no test specified\" && exit 1"},"repository":{"type":"git","url":"git://github.com/mlex/karma-spec-reporter.git"},"keywords":["karma-plugin","reporter"],"author":{"name":"Michael Lex","email":"michael.lex@codecentric.de"},"dependencies":{"colors":"~0.6.0"},"peerDependencies":{"karma":">=0.9"},"license":"MIT","gitHead":"7c5dce5befe30f321950745b6fa2e785f1e1f3ff","bugs":{"url":"https://github.com/mlex/karma-spec-reporter/issues"},"homepage":"https://github.com/mlex/karma-spec-reporter#readme","_id":"karma-spec-reporter@0.0.22","_shasum":"1bbf87b397d1e046235f95edd0d14d4e61b0caa6","_from":".","_npmVersion":"2.11.2","_nodeVersion":"0.12.5","_npmUser":{"name":"tmcgee123","email":"mcgeehonstg@gmail.com"},"dist":{"shasum":"1bbf87b397d1e046235f95edd0d14d4e61b0caa6","tarball":"https://registry.npmjs.org/karma-spec-reporter/-/karma-spec-reporter-0.0.22.tgz"},"maintainers":[{"name":"hdavidzhu","email":"hdavidzhu@gmail.com"},{"name":"mlex","email":"mich.lex@gmail.com"},{"name":"tmcgee123","email":"mcgeehonstg@gmail.com"}],"directories":{}},"0.0.23":{"name":"karma-spec-reporter","version":"0.0.23","description":"A Karma plugin. Report all spec-results to console (like mocha's spec reporter).","main":"index.js","scripts":{"test":"mocha-runner --reporter spec 'test/**/*.spec.js'","coverage":"istanbul cover -x 'test/**/*.js' ./node_modules/.bin/mocha-runner 'test/**/*.js' html text-summary"},"repository":{"type":"git","url":"git://github.com/mlex/karma-spec-reporter.git"},"keywords":["karma-plugin","reporter"],"author":{"name":"Michael Lex","email":"michael.lex@codecentric.de"},"dependencies":{"colors":"~0.6.0"},"peerDependencies":{"karma":">=0.9"},"license":"MIT","devDependencies":{"chai":"^3.4.0","istanbul":"^0.4.0","mocha-runner":"^1.1.1"},"gitHead":"70d5edb3db305d1c1a6c9e4dfd5c014867c6cd64","bugs":{"url":"https://github.com/mlex/karma-spec-reporter/issues"},"homepage":"https://github.com/mlex/karma-spec-reporter#readme","_id":"karma-spec-reporter@0.0.23","_shasum":"d88d0b9f158ce24634029e89dead8a11162c44fd","_from":".","_npmVersion":"3.3.12","_nodeVersion":"5.1.0","_npmUser":{"name":"hdavidzhu","email":"hdavidzhu@gmail.com"},"dist":{"shasum":"d88d0b9f158ce24634029e89dead8a11162c44fd","tarball":"https://registry.npmjs.org/karma-spec-reporter/-/karma-spec-reporter-0.0.23.tgz"},"maintainers":[{"name":"hdavidzhu","email":"hdavidzhu@gmail.com"},{"name":"mlex","email":"mich.lex@gmail.com"},{"name":"tmcgee123","email":"mcgeehonstg@gmail.com"}],"directories":{}},"0.0.24":{"name":"karma-spec-reporter","version":"0.0.24","description":"A Karma plugin. Report all spec-results to console (like mocha's spec reporter).","main":"index.js","scripts":{"test":"mocha-runner --reporter spec 'test/**/*.spec.js'","coverage":"istanbul cover -x 'test/**/*.js' ./node_modules/.bin/mocha-runner -- --reporter spec 'test/**/*.js'"},"repository":{"type":"git","url":"git://github.com/mlex/karma-spec-reporter.git"},"keywords":["karma-plugin","reporter"],"author":{"name":"Michael Lex","email":"michael.lex@codecentric.de"},"dependencies":{"colors":"~0.6.0"},"peerDependencies":{"karma":">=0.9"},"license":"MIT","devDependencies":{"chai":"^3.4.0","coveralls":"^2.11.4","istanbul":"^0.4.0","mocha-runner":"^1.1.1","sinon":"^1.17.2","sinon-chai":"^2.8.0"},"files":["index.js"],"gitHead":"2fb16b187b2c3ce0b807a1575b18e828e8590096","bugs":{"url":"https://github.com/mlex/karma-spec-reporter/issues"},"homepage":"https://github.com/mlex/karma-spec-reporter#readme","_id":"karma-spec-reporter@0.0.24","_shasum":"c68246e0b5ebc8fbeab8a5e959e8de4b12c83dbf","_from":".","_npmVersion":"2.14.12","_nodeVersion":"4.2.4","_npmUser":{"name":"tmcgee123","email":"mcgeehonstg@gmail.com"},"dist":{"shasum":"c68246e0b5ebc8fbeab8a5e959e8de4b12c83dbf","tarball":"https://registry.npmjs.org/karma-spec-reporter/-/karma-spec-reporter-0.0.24.tgz"},"maintainers":[{"name":"hdavidzhu","email":"hdavidzhu@gmail.com"},{"name":"mlex","email":"mich.lex@gmail.com"},{"name":"tmcgee123","email":"mcgeehonstg@gmail.com"}],"_npmOperationalInternal":{"host":"packages-9-west.internal.npmjs.com","tmp":"tmp/karma-spec-reporter-0.0.24.tgz_1455115151511_0.02816590922884643"},"directories":{}},"0.0.25":{"name":"karma-spec-reporter","version":"0.0.25","description":"A Karma plugin. Report all spec-results to console (like mocha's spec reporter).","main":"index.js","scripts":{"test":"mocha-runner --reporter spec 'test/**/*.spec.js'","coverage":"istanbul cover -x 'test/**/*.js' ./node_modules/.bin/mocha-runner -- --reporter spec 'test/**/*.js'"},"repository":{"type":"git","url":"git://github.com/mlex/karma-spec-reporter.git"},"keywords":["karma-plugin","reporter"],"author":{"name":"Michael Lex","email":"michael.lex@codecentric.de"},"dependencies":{"colors":"~0.6.0"},"peerDependencies":{"karma":">=0.9"},"license":"MIT","devDependencies":{"chai":"^3.4.0","coveralls":"^2.11.4","istanbul":"^0.4.0","mocha-runner":"^1.1.1","sinon":"^1.17.2","sinon-chai":"^2.8.0"},"files":["index.js"],"gitHead":"e42aa92db6537b479010a27c300e2c27162a8efc","bugs":{"url":"https://github.com/mlex/karma-spec-reporter/issues"},"homepage":"https://github.com/mlex/karma-spec-reporter#readme","_id":"karma-spec-reporter@0.0.25","_shasum":"8939e615ce9d1be83e31ecf71822e1f3828f5750","_from":".","_npmVersion":"2.11.2","_nodeVersion":"0.12.5","_npmUser":{"name":"tmcgee123","email":"mcgeehonstg@gmail.com"},"dist":{"shasum":"8939e615ce9d1be83e31ecf71822e1f3828f5750","tarball":"https://registry.npmjs.org/karma-spec-reporter/-/karma-spec-reporter-0.0.25.tgz"},"maintainers":[{"name":"hdavidzhu","email":"hdavidzhu@gmail.com"},{"name":"mlex","email":"mich.lex@gmail.com"},{"name":"tmcgee123","email":"mcgeehonstg@gmail.com"}],"_npmOperationalInternal":{"host":"packages-12-west.internal.npmjs.com","tmp":"tmp/karma-spec-reporter-0.0.25.tgz_1459209957576_0.08803747617639601"},"directories":{}},"0.0.26":{"name":"karma-spec-reporter","version":"0.0.26","description":"A Karma plugin. Report all spec-results to console (like mocha's spec reporter).","main":"index.js","scripts":{"test":"mocha-runner --reporter spec 'test/**/*.spec.js'","coverage":"istanbul cover -x 'test/**/*.js' ./node_modules/.bin/mocha-runner -- --reporter spec 'test/**/*.js'"},"repository":{"type":"git","url":"git://github.com/mlex/karma-spec-reporter.git"},"keywords":["karma-plugin","reporter"],"author":{"name":"Michael Lex","email":"michael.lex@codecentric.de"},"dependencies":{"colors":"~0.6.0"},"peerDependencies":{"karma":">=0.9"},"license":"MIT","devDependencies":{"chai":"^3.4.0","coveralls":"^2.11.4","istanbul":"^0.4.0","mocha-runner":"^1.1.1","rewire":"^2.5.1","sinon":"^1.17.2","sinon-chai":"^2.8.0"},"files":["index.js"],"gitHead":"881d19f71e9d7444577332b778eed201a6b72934","bugs":{"url":"https://github.com/mlex/karma-spec-reporter/issues"},"homepage":"https://github.com/mlex/karma-spec-reporter#readme","_id":"karma-spec-reporter@0.0.26","_shasum":"bf5561377dce1b63cf2c975c1af3e35f199e2265","_from":".","_npmVersion":"2.11.2","_nodeVersion":"0.12.5","_npmUser":{"name":"tmcgee123","email":"mcgeehonstg@gmail.com"},"dist":{"shasum":"bf5561377dce1b63cf2c975c1af3e35f199e2265","tarball":"https://registry.npmjs.org/karma-spec-reporter/-/karma-spec-reporter-0.0.26.tgz"},"maintainers":[{"name":"hdavidzhu","email":"hdavidzhu@gmail.com"},{"name":"mlex","email":"mich.lex@gmail.com"},{"name":"tmcgee123","email":"mcgeehonstg@gmail.com"}],"_npmOperationalInternal":{"host":"packages-12-west.internal.npmjs.com","tmp":"tmp/karma-spec-reporter-0.0.26.tgz_1460059422472_0.09134964062832296"},"directories":{}}},"readme":"# karma-spec-reporter\n\n[![Join the chat at https://gitter.im/mlex/karma-spec-reporter](https://badges.gitter.im/Join%20Chat.svg)](https://gitter.im/mlex/karma-spec-reporter?utm_source=badge&utm_medium=badge&utm_campaign=pr-badge&utm_content=badge) [![Build Status](https://travis-ci.org/mlex/karma-spec-reporter.svg)](https://travis-ci.org/mlex/karma-spec-reporter)\n[![Coverage Status](https://coveralls.io/repos/mlex/karma-spec-reporter/badge.svg?branch=master&service=github)](https://coveralls.io/github/mlex/karma-spec-reporter?branch=master)\n\nTest reporter, that prints detailed results to console (similar to mocha's spec reporter).\n\n## Usage\n\nTo use in your own Node.js project, just execute\n```\nnpm install karma-spec-reporter --save-dev\n```\nThis will download the karma-spec-reporter and add the dependency to `package.json`.\n\nThen add ``'spec'`` to reporters in karma.conf.js, e.g.\n\n```\nreporters: ['spec']\n```\n\nTake a look at the [karma-spec-reporter-example](http://github.com/mlex/karma-spec-reporter-example) repository to see the reporter in action.\n\n## Configuration\n\nTo limit the number of lines logged per test or suppress specific reporting, use the `specReporter` configuration in your\nkarma.conf.js file\n``` js\n//karma.conf.js\n...\n  config.set({\n    ...\n      reporters: [\"spec\"],\n      specReporter: {\n        maxLogLines: 5,         // limit number of lines logged per test\n        suppressErrorSummary: true,  // do not print error summary\n        suppressFailed: false,  // do not print information about failed tests\n        suppressPassed: false,  // do not print information about passed tests\n        suppressSkipped: true,  // do not print information about skipped tests\n        showSpecTiming: false // print the time elapsed for each spec\n      },\n      plugins: [\"karma-spec-reporter\"],\n    ...\n```\n\n## Contributing\n\n### Running tests\n\nTo run the tests for the index.js file, run: `npm test`\n\n### Generating Coverage\n\nTo see the coverage report for the module, run: `npm run coverage`\n","maintainers":[{"name":"hdavidzhu","email":"hdavidzhu@gmail.com"},{"name":"mlex","email":"mich.lex@gmail.com"},{"name":"tmcgee123","email":"mcgeehonstg@gmail.com"}],"time":{"modified":"2016-04-07T20:03:44.669Z","created":"2013-05-15T11:49:28.541Z","0.0.1":"2013-05-15T11:49:31.458Z","0.0.2":"2013-07-15T07:05:32.573Z","0.0.3":"2013-07-17T08:55:01.684Z","0.0.4":"2013-08-12T08:07:29.012Z","0.0.5":"2013-09-25T16:28:00.357Z","0.0.6":"2013-10-18T14:23:21.461Z","0.0.7":"2014-01-14T08:10:33.256Z","0.0.8":"2014-01-14T09:09:00.024Z","0.0.9":"2014-02-06T11:41:29.156Z","0.0.10":"2014-02-28T16:10:24.207Z","0.0.11":"2014-03-17T09:07:55.553Z","0.0.12":"2014-03-17T09:10:42.361Z","0.0.13":"2014-05-19T13:17:21.333Z","0.0.14":"2014-12-15T09:56:58.257Z","0.0.15":"2014-12-15T10:00:36.022Z","0.0.16":"2014-12-15T10:24:12.048Z","0.0.17":"2015-03-27T17:43:12.176Z","0.0.18":"2015-03-27T17:59:20.214Z","0.0.19":"2015-04-16T20:17:12.467Z","0.0.20":"2015-07-13T13:26:19.387Z","0.0.21":"2015-10-23T08:16:54.547Z","0.0.22":"2015-10-28T14:50:20.475Z","0.0.23":"2015-11-25T23:10:24.698Z","0.0.24":"2016-02-10T14:39:14.688Z","0.0.25":"2016-03-29T00:06:00.020Z","0.0.26":"2016-04-07T20:03:44.669Z"},"author":{"name":"Michael Lex","email":"michael.lex@codecentric.de"},"repository":{"type":"git","url":"git://github.com/mlex/karma-spec-reporter.git"},"readmeFilename":"README.md","keywords":["karma-plugin","reporter"],"license":"MIT","users":{"lokua":true,"jmorris":true,"monolithed":true,"mccataldo":true,"ristostevcev":true,"yqrashawn":true},"homepage":"https://github.com/mlex/karma-spec-reporter#readme","bugs":{"url":"https://github.com/mlex/karma-spec-reporter/issues"},"_attachments":{},"_etag":"\"CCS3S2BBWRPDDZY85R5IHALJJ\""}